dojo_exporter/collector.py
dojo_exporter-0.1.4.dist-info/LICENSE
dojo_exporter-0.1.4.dist-info/METADATA
dojo_exporter-0.1.4.dist-info/WHEEL
dojo_exporter-0.1.4.dist-info/entry_points.txt
dojo_exporter-0.1.4.dist-info/top_level.txt
dojo_exporter-0.1.4.dist-info/RECORD
