Metadata-Version: 2.1
Name: dojo-exporter
Version: 0.1.4
Summary: Devops monitoring tool for Samourai Dojo
Author-email: blee <blee@bitcoiner.social>
License: Apache License
Project-URL: Homepage, https://github.com/bleetube/dojo_exporter
Keywords: samourai
Classifier: Programming Language :: Python
Classifier: Programming Language :: Python :: 3
Classifier: Programming Language :: Python :: 3.8
Classifier: Programming Language :: Python :: 3.9
Classifier: Programming Language :: Python :: 3.10
Classifier: Programming Language :: Python :: Implementation :: CPython
Classifier: Programming Language :: Python :: Implementation :: PyPy
Classifier: Topic :: System :: Monitoring
Classifier: License :: OSI Approved :: Apache Software License
Requires-Python: >=3.8.10
License-File: LICENSE
Requires-Dist: build (>=0.8.0)
Requires-Dist: prometheus-client (>=0.15.0)
Requires-Dist: bitmath (>=1.3.3.1)
Requires-Dist: python-dotenv (>=1.0.0)
